h2p/__init__.py
h2p/_wkhtmltopdf.py
h2p/h2p.py
h2p-0.1.0.dist-info/DESCRIPTION.rst
h2p-0.1.0.dist-info/METADATA
h2p-0.1.0.dist-info/RECORD
h2p-0.1.0.dist-info/WHEEL
h2p-0.1.0.dist-info/metadata.json
h2p-0.1.0.dist-info/top_level.txt
