Metadata-Version: 2.0
Name: h2p
Version: 0.1.0
Summary: Convert HTML files to PDFs.
Home-page: UNKNOWN
Author: UNKNOWN
Author-email: UNKNOWN
License: UNKNOWN
Platform: UNKNOWN
